mazer/__init__.py
mazer/apps.py
mazer/compat.py
mazer/settings.py
mazer/utils.py
mazer/widgets.py
mazer/templatetags/__init__.py
mazer/templatetags/mazer.py
django_mazer_megaelebrus-0.0.1.dist-info/LICENSE
django_mazer_megaelebrus-0.0.1.dist-info/METADATA
django_mazer_megaelebrus-0.0.1.dist-info/WHEEL
django_mazer_megaelebrus-0.0.1.dist-info/top_level.txt
django_mazer_megaelebrus-0.0.1.dist-info/RECORD
